pymodaq_plugins_princeton_instruments/VERSION
pymodaq_plugins_princeton_instruments/__init__.py
pymodaq_plugins_princeton_instruments/daq_move_plugins/__init__.py
pymodaq_plugins_princeton_instruments/daq_viewer_plugins/__init__.py
pymodaq_plugins_princeton_instruments/daq_viewer_plugins/plugins_0D/__init__.py
pymodaq_plugins_princeton_instruments/daq_viewer_plugins/plugins_1D/__init__.py
pymodaq_plugins_princeton_instruments/daq_viewer_plugins/plugins_2D/__init__.py
pymodaq_plugins_princeton_instruments/daq_viewer_plugins/plugins_2D/daq_2Dviewer_picam.py
pymodaq_plugins_princeton_instruments/daq_viewer_plugins/plugins_ND/__init__.py
pymodaq_plugins_princeton_instruments/hardware/__init__.py
pymodaq_plugins_princeton_instruments/hardware/picam_utils.py
pymodaq_plugins_princeton_instruments-0.1.0.dist-info/LICENSE
pymodaq_plugins_princeton_instruments-0.1.0.dist-info/METADATA
pymodaq_plugins_princeton_instruments-0.1.0.dist-info/WHEEL
pymodaq_plugins_princeton_instruments-0.1.0.dist-info/entry_points.txt
pymodaq_plugins_princeton_instruments-0.1.0.dist-info/top_level.txt
pymodaq_plugins_princeton_instruments-0.1.0.dist-info/RECORD
