Metadata-Version: 2.1
Name: pymodaq-plugins-princeton-instruments
Version: 0.1.0
Summary: Control for hyperspy of scientific cameras using the picam library
Home-page: https://github.com/LMSC-NTappy/pymodaq_plugins_princeton_instruments/
Author: Nicolas Tappy
Author-email: nicolas.tappy@epfl.ch
License: MIT
Classifier: Programming Language :: Python :: 3
Classifier: Development Status :: 4 - Beta
Classifier: Environment :: Other Environment
Classifier: Intended Audience :: Science/Research
Classifier: Topic :: Scientific/Engineering :: Human Machine Interfaces
Classifier: Topic :: Scientific/Engineering :: Visualization
Classifier: License :: OSI Approved :: MIT License
Classifier: Operating System :: OS Independent
Classifier: Topic :: Software Development :: Libraries :: Python Modules
Classifier: Topic :: Software Development :: User Interfaces
License-File: LICENSE
Requires-Dist: toml
Requires-Dist: pylablib
